clockify_sdk/__init__.py
clockify_sdk/client.py
clockify_sdk/config.py
clockify_sdk/connection.py
clockify_sdk/exceptions.py
clockify_sdk/logging.py
clockify_sdk/base/client.py
clockify_sdk/base/connection.py
clockify_sdk/models/base.py
clockify_sdk/models/client.py
clockify_sdk/models/project.py
clockify_sdk/models/report.py
clockify_sdk/models/task.py
clockify_sdk/models/time_entry.py
clockify_sdk/models/user.py
clockify_sdk/utils/date_utils.py
clockify_sdk-0.2.2.dist-info/METADATA
clockify_sdk-0.2.2.dist-info/WHEEL
clockify_sdk-0.2.2.dist-info/licenses/LICENSE
clockify_sdk-0.2.2.dist-info/RECORD
