Metadata-Version: 2.4
Name: clockify-sdk
Version: 0.2.2
Summary: A Python SDK for interacting with the Clockify API
Project-URL: Repository, https://github.com/fraqtory/clockify-sdk
Project-URL: Documentation, https://clockify-sdk.readthedocs.io
Author-email: Fraqtory <fraqtory@gmail.com>
License-Expression: MIT
License-File: LICENSE
Keywords: api,clockify,sdk,time tracking
Classifier: Intended Audience :: Developers
Classifier: License :: OSI Approved :: MIT License
Classifier: Programming Language :: Python :: 3
Classifier: Programming Language :: Python :: 3.10
Classifier: Programming Language :: Python :: 3.11
Classifier: Programming Language :: Python :: 3.12
Classifier: Topic :: Software Development :: Libraries :: Python Modules
Requires-Python: >=3.8
Requires-Dist: pydantic>=2.6.0
Requires-Dist: python-dateutil>=2.8.2
Requires-Dist: python-dotenv>=1.0.0
Requires-Dist: requests>=2.31.0
Requires-Dist: typing-extensions>=4.8.0
Requires-Dist: urllib3>=2.1.0
Provides-Extra: dev
Requires-Dist: bandit>=1.7.5; extra == 'dev'
Requires-Dist: black>=23.9.1; extra == 'dev'
Requires-Dist: isort>=5.12.0; extra == 'dev'
Requires-Dist: mypy>=1.7.0; extra == 'dev'
Requires-Dist: pytest-cov>=4.1.0; extra == 'dev'
Requires-Dist: pytest>=7.4.0; extra == 'dev'
Requires-Dist: ruff>=0.1.3; extra == 'dev'
Requires-Dist: types-requests>=2.31.0.20240311; extra == 'dev'
Provides-Extra: docs
Requires-Dist: sphinx-rtd-theme>=1.3.0; extra == 'docs'
Requires-Dist: sphinx>=7.0.0; extra == 'docs'
